tftabular/__init__.py
tftabular/layers.py
tftabular/models.py
tftabular/utils.py
tftabular-0.1.3.dist-info/LICENSE
tftabular-0.1.3.dist-info/WHEEL
tftabular-0.1.3.dist-info/METADATA
tftabular-0.1.3.dist-info/RECORD
